Workbook

Sheet Dashboard
A1: Dashboard
A2: Everything on this sheet is calculated. Enter your data in Income and Expenses.
A5: Total invoiced | B5: =SUM(Income!E4:E303) -> 1500 | D5: Unpaid invoices | E5: =COUNTIF(Income!G4:G303,"Unpaid") -> 0
A6: Total received | B6: =SUMPRODUCT((Income!$F$4:$F$303<>"")*Income!$E$4:$E$303) -> 1500 | D6: Amount outstanding | E6: =B7 -> 0
A7: Outstanding | B7: =B5-B6 -> 0 | D7: Active clients | E7: =SUMPRODUCT((Income!$B$4:$B$303<>"")/COUNTIF(Income!$B$4:$B$303,Income!$B$4:$B$303&"")) -> 1
A8: Total expenses | B8: =SUM(Expenses!E4:E303) -> 59.99
A9: Profit | B9: =B5-B8 -> 1440.01
A10: Tax set-aside | B10: =IF(B9>0,B9*Settings!B5,0) -> 360.0025
A11: Net after tax | B11: =B9-B10 -> 1080.0075
A12: Profit margin | B12: =IFERROR(B9/B5,0) -> 0.96000667
A15: Expenses by category
A16: =IF(Settings!C11="","",Settings!C11) -> Software | B16: =IF($A16="","",SUMIF(Expenses!$D$4:$D$303,$A16,Expenses!$E$4:$E$303)) -> 59.99
A17: =IF(Settings!C12="","",Settings!C12) -> Hardware | B17: =IF($A17="","",SUMIF(Expenses!$D$4:$D$303,$A17,Expenses!$E$4:$E$303)) -> 0
A18: =IF(Settings!C13="","",Settings!C13) -> Subcontractors | B18: =IF($A18="","",SUMIF(Expenses!$D$4:$D$303,$A18,Expenses!$E$4:$E$303)) -> 0
A19: =IF(Settings!C14="","",Settings!C14) -> Marketing | B19: =IF($A19="","",SUMIF(Expenses!$D$4:$D$303,$A19,Expenses!$E$4:$E$303)) -> 0
A20: =IF(Settings!C15="","",Settings!C15) -> Travel | B20: =IF($A20="","",SUMIF(Expenses!$D$4:$D$303,$A20,Expenses!$E$4:$E$303)) -> 0
A21: =IF(Settings!C16="","",Settings!C16) -> Office | B21: =IF($A21="","",SUMIF(Expenses!$D$4:$D$303,$A21,Expenses!$E$4:$E$303)) -> 0
A22: =IF(Settings!C17="","",Settings!C17) -> Professional fees | B22: =IF($A22="","",SUMIF(Expenses!$D$4:$D$303,$A22,Expenses!$E$4:$E$303)) -> 0
A23: =IF(Settings!C18="","",Settings!C18) -> Training | B23: =IF($A23="","",SUMIF(Expenses!$D$4:$D$303,$A23,Expenses!$E$4:$E$303)) -> 0
A24: =IF(Settings!C19="","",Settings!C19) -> Insurance | B24: =IF($A24="","",SUMIF(Expenses!$D$4:$D$303,$A24,Expenses!$E$4:$E$303)) -> 0
A25: =IF(Settings!C20="","",Settings!C20) -> Bank fees | B25: =IF($A25="","",SUMIF(Expenses!$D$4:$D$303,$A25,Expenses!$E$4:$E$303)) -> 0
A26: =IF(Settings!C21="","",Settings!C21) -> Other | B26: =IF($A26="","",SUMIF(Expenses!$D$4:$D$303,$A26,Expenses!$E$4:$E$303)) -> 0

Sheet Start Here
A1: Freelancer Finance Tracker
A4: HOW THIS WORKBOOK WORKS
B5: You only ever type in three sheets. Everything else calculates itself.
A7: 1. Settings | B7: Set your tax rate and edit the category lists. Do this once.
A8: 2. Income | B8: Log every invoice. One row per invoice.
A9: 3. Expenses | B9: Log every business expense. One row per expense.
A11: Dashboard | B11: Reads automatically. Never type here.
A12: Monthly Summary | B12: Reads automatically. Never type here.
A13: Clients | B13: Reads automatically. Shows which clients are actually worth it.
A15: COLOUR KEY
B16: Yellow cells are for you to fill in.
B17: White cells contain formulas. Typing over one breaks it.
A19: BEFORE YOU START
B20: Each log sheet has one example row so you can see the expected format.
B21: Delete it once you have entered your own data.
A23: A NOTE ON TAX
B24: The tax set-aside is a planning estimate based on the rate you enter.
B25: It is not tax advice and does not replace an accountant.

Sheet Settings
A1: Settings
A3: Set these once
A5: Tax set-aside rate | B5: 0.25 | C5: Percentage of profit to reserve for tax. Ask your accountant.
A6: Business name | B6: Your Business
A7: Currency symbol shown | B7: $ | C7: Cosmetic only. Change cell formats to switch currency fully.
A10: Income categories | C10: Expense categories
A11: Client work | C11: Software
A12: Retainer | C12: Hardware
A13: Consulting | C13: Subcontractors
A14: Royalties | C14: Marketing
A15: Teaching | C15: Travel
A16: Affiliate | C16: Office
A17: Other | C17: Professional fees
C18: Training
C19: Insurance
C20: Bank fees
C21: Other

Sheet Income
A1: Income — one row per invoice
A2: Yellow = type here. Leave 'Date paid' empty until the invoice is actually paid.
A3: Date issued | B3: Client | C3: Description | D3: Category | E3: Amount | F3: Date paid | G3: Status
A4: 2026-01-15 | B4: Acme Ltd | C4: Website redesign — phase 1 | D4: Client work | E4: 1500 | F4: 2026-02-02 | G4: =IF(E4="","",IF(F4="","Unpaid","Paid")) -> Paid
G5: =IF(E5="","",IF(F5="","Unpaid","Paid"))
G6: =IF(E6="","",IF(F6="","Unpaid","Paid"))
G7: =IF(E7="","",IF(F7="","Unpaid","Paid"))
G8: =IF(E8="","",IF(F8="","Unpaid","Paid"))
G9: =IF(E9="","",IF(F9="","Unpaid","Paid"))
G10: =IF(E10="","",IF(F10="","Unpaid","Paid"))
G11: =IF(E11="","",IF(F11="","Unpaid","Paid"))
G12: =IF(E12="","",IF(F12="","Unpaid","Paid"))
G13: =IF(E13="","",IF(F13="","Unpaid","Paid"))
G14: =IF(E14="","",IF(F14="","Unpaid","Paid"))
G15: =IF(E15="","",IF(F15="","Unpaid","Paid"))
G16: =IF(E16="","",IF(F16="","Unpaid","Paid"))
... G303: =IF(E303="","",IF(F303="","Unpaid","Paid"))

Sheet Expenses
A1: Expenses — one row per expense
A2: Yellow = type here. Mark 'Deductible' as Yes or No.
A3: Date | B3: Supplier | C3: Description | D3: Category | E3: Amount | F3: Deductible
A4: 2026-01-08 | B4: Adobe | C4: Creative Cloud subscription | D4: Software | E4: 59.99 | F4: Yes

Sheet Monthly Summary
A1: Monthly Summary — calculated automatically
A2: Every figure here is a formula. Do not type in this sheet.
A3: Month | B3: Income invoiced | C3: Income received | D3: Expenses | E3: Profit | F3: Tax set-aside | G3: Net after tax
A4: 2026-01 | B4: =SUMPRODUCT((LEFT(Income!$A$4:$A$303,7)=$A4)*Income!$E$4:$E$303) -> 1500 | C4: =SUMPRODUCT((LEFT(Income!$F$4:$F$303,7)=$A4)*Income!$E$4:$E$303) -> 0 | D4: =SUMPRODUCT((LEFT(Expenses!$A$4:$A$303,7)=$A4)*Expenses!$E$4:$E$303) -> 59.99 | E4: =B4-D4 -> 1440.01 | F4: =IF(E4>0,E4*Settings!$B$5,0) -> 360.0025 | G4: =E4-F4 -> 1080.0075
A5: 2026-02 | B5: =SUMPRODUCT((LEFT(Income!$A$4:$A$303,7)=$A5)*Income!$E$4:$E$303) -> 0 | C5: =SUMPRODUCT((LEFT(Income!$F$4:$F$303,7)=$A5)*Income!$E$4:$E$303) -> 1500 | D5: =SUMPRODUCT((LEFT(Expenses!$A$4:$A$303,7)=$A5)*Expenses!$E$4:$E$303) -> 0 | E5: =B5-D5 -> 0 | F5: =IF(E5>0,E5*Settings!$B$5,0) -> 0 | G5: =E5-F5 -> 0
A6: 2026-03 | B6: =SUMPRODUCT((LEFT(Income!$A$4:$A$303,7)=$A6)*Income!$E$4:$E$303) -> 0 | C6: =SUMPRODUCT((LEFT(Income!$F$4:$F$303,7)=$A6)*Income!$E$4:$E$303) -> 0 | D6: =SUMPRODUCT((LEFT(Expenses!$A$4:$A$303,7)=$A6)*Expenses!$E$4:$E$303) -> 0 | E6: =B6-D6 -> 0 | F6: =IF(E6>0,E6*Settings!$B$5,0) -> 0 | G6: =E6-F6 -> 0
A7: 2026-04 | B7: =SUMPRODUCT((LEFT(Income!$A$4:$A$303,7)=$A7)*Income!$E$4:$E$303) -> 0 | C7: =SUMPRODUCT((LEFT(Income!$F$4:$F$303,7)=$A7)*Income!$E$4:$E$303) -> 0 | D7: =SUMPRODUCT((LEFT(Expenses!$A$4:$A$303,7)=$A7)*Expenses!$E$4:$E$303) -> 0 | E7: =B7-D7 -> 0 | F7: =IF(E7>0,E7*Settings!$B$5,0) -> 0 | G7: =E7-F7 -> 0
A8: 2026-05 | B8: =SUMPRODUCT((LEFT(Income!$A$4:$A$303,7)=$A8)*Income!$E$4:$E$303) -> 0 | C8: =SUMPRODUCT((LEFT(Income!$F$4:$F$303,7)=$A8)*Income!$E$4:$E$303) -> 0 | D8: =SUMPRODUCT((LEFT(Expenses!$A$4:$A$303,7)=$A8)*Expenses!$E$4:$E$303) -> 0 | E8: =B8-D8 -> 0 | F8: =IF(E8>0,E8*Settings!$B$5,0) -> 0 | G8: =E8-F8 -> 0
A9: 2026-06 | B9: =SUMPRODUCT((LEFT(Income!$A$4:$A$303,7)=$A9)*Income!$E$4:$E$303) -> 0 | C9: =SUMPRODUCT((LEFT(Income!$F$4:$F$303,7)=$A9)*Income!$E$4:$E$303) -> 0 | D9: =SUMPRODUCT((LEFT(Expenses!$A$4:$A$303,7)=$A9)*Expenses!$E$4:$E$303) -> 0 | E9: =B9-D9 -> 0 | F9: =IF(E9>0,E9*Settings!$B$5,0) -> 0 | G9: =E9-F9 -> 0
A10: 2026-07 | B10: =SUMPRODUCT((LEFT(Income!$A$4:$A$303,7)=$A10)*Income!$E$4:$E$303) -> 0 | C10: =SUMPRODUCT((LEFT(Income!$F$4:$F$303,7)=$A10)*Income!$E$4:$E$303) -> 0 | D10: =SUMPRODUCT((LEFT(Expenses!$A$4:$A$303,7)=$A10)*Expenses!$E$4:$E$303) -> 0 | E10: =B10-D10 -> 0 | F10: =IF(E10>0,E10*Settings!$B$5,0) -> 0 | G10: =E10-F10 -> 0
A11: 2026-08 | B11: =SUMPRODUCT((LEFT(Income!$A$4:$A$303,7)=$A11)*Income!$E$4:$E$303) -> 0 | C11: =SUMPRODUCT((LEFT(Income!$F$4:$F$303,7)=$A11)*Income!$E$4:$E$303) -> 0 | D11: =SUMPRODUCT((LEFT(Expenses!$A$4:$A$303,7)=$A11)*Expenses!$E$4:$E$303) -> 0 | E11: =B11-D11 -> 0 | F11: =IF(E11>0,E11*Settings!$B$5,0) -> 0 | G11: =E11-F11 -> 0
A12: 2026-09 | B12: =SUMPRODUCT((LEFT(Income!$A$4:$A$303,7)=$A12)*Income!$E$4:$E$303) -> 0 | C12: =SUMPRODUCT((LEFT(Income!$F$4:$F$303,7)=$A12)*Income!$E$4:$E$303) -> 0 | D12: =SUMPRODUCT((LEFT(Expenses!$A$4:$A$303,7)=$A12)*Expenses!$E$4:$E$303) -> 0 | E12: =B12-D12 -> 0 | F12: =IF(E12>0,E12*Settings!$B$5,0) -> 0 | G12: =E12-F12 -> 0
A13: 2026-10 | B13: =SUMPRODUCT((LEFT(Income!$A$4:$A$303,7)=$A13)*Income!$E$4:$E$303) -> 0 | C13: =SUMPRODUCT((LEFT(Income!$F$4:$F$303,7)=$A13)*Income!$E$4:$E$303) -> 0 | D13: =SUMPRODUCT((LEFT(Expenses!$A$4:$A$303,7)=$A13)*Expenses!$E$4:$E$303) -> 0 | E13: =B13-D13 -> 0 | F13: =IF(E13>0,E13*Settings!$B$5,0) -> 0 | G13: =E13-F13 -> 0
A14: 2026-11 | B14: =SUMPRODUCT((LEFT(Income!$A$4:$A$303,7)=$A14)*Income!$E$4:$E$303) -> 0 | C14: =SUMPRODUCT((LEFT(Income!$F$4:$F$303,7)=$A14)*Income!$E$4:$E$303) -> 0 | D14: =SUMPRODUCT((LEFT(Expenses!$A$4:$A$303,7)=$A14)*Expenses!$E$4:$E$303) -> 0 | E14: =B14-D14 -> 0 | F14: =IF(E14>0,E14*Settings!$B$5,0) -> 0 | G14: =E14-F14 -> 0
A15: 2026-12 | B15: =SUMPRODUCT((LEFT(Income!$A$4:$A$303,7)=$A15)*Income!$E$4:$E$303) -> 0 | C15: =SUMPRODUCT((LEFT(Income!$F$4:$F$303,7)=$A15)*Income!$E$4:$E$303) -> 0 | D15: =SUMPRODUCT((LEFT(Expenses!$A$4:$A$303,7)=$A15)*Expenses!$E$4:$E$303) -> 0 | E15: =B15-D15 -> 0 | F15: =IF(E15>0,E15*Settings!$B$5,0) -> 0 | G15: =E15-F15 -> 0
A16: TOTAL | B16: =SUM(B4:B15) -> 1500 | C16: =SUM(C4:C15) -> 1500 | D16: =SUM(D4:D15) -> 59.99 | E16: =SUM(E4:E15) -> 1440.01 | F16: =SUM(F4:F15) -> 360.0025 | G16: =SUM(G4:G15) -> 1080.0075

Sheet Clients
A1: Clients — who is actually worth your time
A2: Type a client name in column A exactly as written in the Income sheet. The rest calculates.
A3: Client | B3: Invoiced | C3: Received | D3: Outstanding | E3: Invoices | F3: % of total income
B4: =IF($A4="","",SUMIF(Income!$B$4:$B$303,$A4,Income!$E$4:$E$303)) | C4: =IF($A4="","",SUMPRODUCT((Income!$B$4:$B$303=$A4)*(Income!$F$4:$F$303<>"")*Income!$E$4:$E$303)) | D4: =IF($A4="","",B4-C4) | E4: =IF($A4="","",COUNTIF(Income!$B$4:$B$303,$A4)) | F4: =IF(OR($A4="",SUM(Income!$E$4:$E$303)=0),"",B4/SUM(Income!$E$4:$E$303))
B5: =IF($A5="","",SUMIF(Income!$B$4:$B$303,$A5,Income!$E$4:$E$303)) | C5: =IF($A5="","",SUMPRODUCT((Income!$B$4:$B$303=$A5)*(Income!$F$4:$F$303<>"")*Income!$E$4:$E$303)) | D5: =IF($A5="","",B5-C5) | E5: =IF($A5="","",COUNTIF(Income!$B$4:$B$303,$A5)) | F5: =IF(OR($A5="",SUM(Income!$E$4:$E$303)=0),"",B5/SUM(Income!$E$4:$E$303))
B6: =IF($A6="","",SUMIF(Income!$B$4:$B$303,$A6,Income!$E$4:$E$303)) | C6: =IF($A6="","",SUMPRODUCT((Income!$B$4:$B$303=$A6)*(Income!$F$4:$F$303<>"")*Income!$E$4:$E$303)) | D6: =IF($A6="","",B6-C6) | E6: =IF($A6="","",COUNTIF(Income!$B$4:$B$303,$A6)) | F6: =IF(OR($A6="",SUM(Income!$E$4:$E$303)=0),"",B6/SUM(Income!$E$4:$E$303))
B7: =IF($A7="","",SUMIF(Income!$B$4:$B$303,$A7,Income!$E$4:$E$303)) | C7: =IF($A7="","",SUMPRODUCT((Income!$B$4:$B$303=$A7)*(Income!$F$4:$F$303<>"")*Income!$E$4:$E$303)) | D7: =IF($A7="","",B7-C7) | E7: =IF($A7="","",COUNTIF(Income!$B$4:$B$303,$A7)) | F7: =IF(OR($A7="",SUM(Income!$E$4:$E$303)=0),"",B7/SUM(Income!$E$4:$E$303))
B8: =IF($A8="","",SUMIF(Income!$B$4:$B$303,$A8,Income!$E$4:$E$303)) | C8: =IF($A8="","",SUMPRODUCT((Income!$B$4:$B$303=$A8)*(Income!$F$4:$F$303<>"")*Income!$E$4:$E$303)) | D8: =IF($A8="","",B8-C8) | E8: =IF($A8="","",COUNTIF(Income!$B$4:$B$303,$A8)) | F8: =IF(OR($A8="",SUM(Income!$E$4:$E$303)=0),"",B8/SUM(Income!$E$4:$E$303))
B9: =IF($A9="","",SUMIF(Income!$B$4:$B$303,$A9,Income!$E$4:$E$303)) | C9: =IF($A9="","",SUMPRODUCT((Income!$B$4:$B$303=$A9)*(Income!$F$4:$F$303<>"")*Income!$E$4:$E$303)) | D9: =IF($A9="","",B9-C9) | E9: =IF($A9="","",COUNTIF(Income!$B$4:$B$303,$A9)) | F9: =IF(OR($A9="",SUM(Income!$E$4:$E$303)=0),"",B9/SUM(Income!$E$4:$E$303))
B10: =IF($A10="","",SUMIF(Income!$B$4:$B$303,$A10,Income!$E$4:$E$303)) | C10: =IF($A10="","",SUMPRODUCT((Income!$B$4:$B$303=$A10)*(Income!$F$4:$F$303<>"")*Income!$E$4:$E$303)) | D10: =IF($A10="","",B10-C10) | E10: =IF($A10="","",COUNTIF(Income!$B$4:$B$303,$A10)) | F10: =IF(OR($A10="",SUM(Income!$E$4:$E$303)=0),"",B10/SUM(Income!$E$4:$E$303))
B11: =IF($A11="","",SUMIF(Income!$B$4:$B$303,$A11,Income!$E$4:$E$303)) | C11: =IF($A11="","",SUMPRODUCT((Income!$B$4:$B$303=$A11)*(Income!$F$4:$F$303<>"")*Income!$E$4:$E$303)) | D11: =IF($A11="","",B11-C11) | E11: =IF($A11="","",COUNTIF(Income!$B$4:$B$303,$A11)) | F11: =IF(OR($A11="",SUM(Income!$E$4:$E$303)=0),"",B11/SUM(Income!$E$4:$E$303))
B12: =IF($A12="","",SUMIF(Income!$B$4:$B$303,$A12,Income!$E$4:$E$303)) | C12: =IF($A12="","",SUMPRODUCT((Income!$B$4:$B$303=$A12)*(Income!$F$4:$F$303<>"")*Income!$E$4:$E$303)) | D12: =IF($A12="","",B12-C12) | E12: =IF($A12="","",COUNTIF(Income!$B$4:$B$303,$A12)) | F12: =IF(OR($A12="",SUM(Income!$E$4:$E$303)=0),"",B12/SUM(Income!$E$4:$E$303))
B13: =IF($A13="","",SUMIF(Income!$B$4:$B$303,$A13,Income!$E$4:$E$303)) | C13: =IF($A13="","",SUMPRODUCT((Income!$B$4:$B$303=$A13)*(Income!$F$4:$F$303<>"")*Income!$E$4:$E$303)) | D13: =IF($A13="","",B13-C13) | E13: =IF($A13="","",COUNTIF(Income!$B$4:$B$303,$A13)) | F13: =IF(OR($A13="",SUM(Income!$E$4:$E$303)=0),"",B13/SUM(Income!$E$4:$E$303))
B14: =IF($A14="","",SUMIF(Income!$B$4:$B$303,$A14,Income!$E$4:$E$303)) | C14: =IF($A14="","",SUMPRODUCT((Income!$B$4:$B$303=$A14)*(Income!$F$4:$F$303<>"")*Income!$E$4:$E$303)) | D14: =IF($A14="","",B14-C14) | E14: =IF($A14="","",COUNTIF(Income!$B$4:$B$303,$A14)) | F14: =IF(OR($A14="",SUM(Income!$E$4:$E$303)=0),"",B14/SUM(Income!$E$4:$E$303))
B15: =IF($A15="","",SUMIF(Income!$B$4:$B$303,$A15,Income!$E$4:$E$303)) | C15: =IF($A15="","",SUMPRODUCT((Income!$B$4:$B$303=$A15)*(Income!$F$4:$F$303<>"")*Income!$E$4:$E$303)) | D15: =IF($A15="","",B15-C15) | E15: =IF($A15="","",COUNTIF(Income!$B$4:$B$303,$A15)) | F15: =IF(OR($A15="",SUM(Income!$E$4:$E$303)=0),"",B15/SUM(Income!$E$4:$E$303))
... B33: =IF($A33="","",SUMIF(Income!$B$4:$B$303,$A33,Income!$E$4:$E$303)) | C33: =IF($A33="","",SUMPRODUCT((Income!$B$4:$B$303=$A33)*(Income!$F$4:$F$303<>"")*Income!$E$4:$E$303)) | D33: =IF($A33="","",B33-C33) | E33: =IF($A33="","",COUNTIF(Income!$B$4:$B$303,$A33)) | F33: =IF(OR($A33="",SUM(Income!$E$4:$E$303)=0),"",B33/SUM(Income!$E$4:$E$303))
